core/__init__.py
gs_java-0.1.1.dist-info/METADATA
gs_java-0.1.1.dist-info/WHEEL
gs_java-0.1.1.dist-info/top_level.txt
gs_java-0.1.1.dist-info/RECORD
